eagle/__init__.py
eagle/agents/__init__.py
eagle/agents/base.py
eagle/agents/react_agent/__init__.py
eagle/agents/react_agent/base.py
eagle/agents/react_agent/prompts.py
eagle/agents/specialists/__init__.py
eagle/agents/specialists/coding/__init__.py
eagle/agents/specialists/coding/base.py
eagle/agents/specialists/coding/prompts.py
eagle/chains/plan_processing.py
eagle/chains/plan_qa.py
eagle/chains/translation.py
eagle/chat_schemas/__init__.py
eagle/chat_schemas/base.py
eagle/chat_schemas/debate_schemas/__init__.py
eagle/chat_schemas/debate_schemas/agents/__init__.py
eagle/chat_schemas/debate_schemas/agents/prompts.py
eagle/chat_schemas/debate_schemas/agents/supervisor.py
eagle/chat_schemas/debate_schemas/schemas.py
eagle/memory/__init__.py
eagle/memory/base.py
eagle/memory/episodic/__init__.py
eagle/memory/episodic/base.py
eagle/memory/episodic/conversation_history_memory.py
eagle/memory/generic/base.py
eagle/memory/planning/__init__.py
eagle/memory/planning/base.py
eagle/memory/planning/possible_plans_and_tools_memory.py
eagle/memory/planning/possible_plans_memory.py
eagle/memory/planning/possible_tools_memory.py
eagle/memory/shared/__init__.py
eagle/memory/shared/base.py
eagle/memory/shared/shared_objects_memory.py
eagle/stores/__init__.py
eagle/stores/base.py
eagle/stores/opensearch.py
eagle/tools/__init__.py
eagle/tools/finance/__init__.py
eagle/tools/finance/yfinance.py
eagle/tools/math/__init__.py
eagle/tools/math/sum_tools.py
eagle/tools/memory_access/__init__.py
eagle/tools/memory_access/generic_memory_tool.py
eagle/tools/memory_access/planning/__init__.py
eagle/tools/memory_access/planning/possible_plans.py
eagle/tools/pandas_handling/__init__.py
eagle/tools/pandas_handling/pandas_dataframe_query.py
eagle/tools/search_engines/__init__.py
eagle/tools/search_engines/arxiv.py
eagle/tools/search_engines/ddg_search.py
eagle/tools/search_engines/google_scholar.py
eagle/tools/tool_configuration_schemas.py
eagle/utils/classes_utils.py
eagle/utils/configs.py
teste_lr_eagle_020602025-0.0.0.dist-info/METADATA
teste_lr_eagle_020602025-0.0.0.dist-info/WHEEL
teste_lr_eagle_020602025-0.0.0.dist-info/RECORD
